dola_sui_sdk/__init__.py
dola_sui_sdk/deploy.py
dola_sui_sdk/init.py
dola_sui_sdk/interfaces.py
dola_sui_sdk/lending.py
dola_sui_sdk/load.py
dola_sui_sdk-0.0.8.dist-info/METADATA
dola_sui_sdk-0.0.8.dist-info/WHEEL
dola_sui_sdk-0.0.8.dist-info/top_level.txt
dola_sui_sdk-0.0.8.dist-info/RECORD
