Metadata-Version: 2.1
Name: dola-sui-sdk
Version: 0.0.8
Summary: Dola Sui SDK
Home-page: https://github.com/OmniBTC/DolaProtocol/blob/main/sui/scripts/dola_sui_sdk
Author: DaiWei
Author-email: dw1253464613@gmail.com
License: MIT
Classifier: Development Status :: 4 - Beta
Classifier: Intended Audience :: Developers
Classifier: Topic :: System :: Logging
Classifier: License :: OSI Approved :: MIT License
Classifier: Programming Language :: Python :: 3
Classifier: Programming Language :: Python :: 3.3
Classifier: Programming Language :: Python :: 3.4
Classifier: Programming Language :: Python :: 3.5
Classifier: Programming Language :: Python :: 3.6
Classifier: Programming Language :: Python :: 3.7
Classifier: Programming Language :: Python :: 3.8
Requires-Python: >=3.6
Requires-Dist: sui-brownie
